LICENSE
MANIFEST.in
README.md
setup.py
mlbstreamer/__init__.py
mlbstreamer/__main__.py
mlbstreamer/config.py
mlbstreamer/play.py
mlbstreamer/session.py
mlbstreamer/state.py
mlbstreamer/util.py
mlbstreamer/widgets.py
mlbstreamer.egg-info/PKG-INFO
mlbstreamer.egg-info/SOURCES.txt
mlbstreamer.egg-info/dependency_links.txt
mlbstreamer.egg-info/entry_points.txt
mlbstreamer.egg-info/requires.txt
mlbstreamer.egg-info/top_level.txt
test/__init__.py
test/test_mlbplay.py