Metadata-Version: 1.1
Name: mlbstreamer
Version: 0.0.10
Summary: MLB.tv Stream Browser
Home-page: https://github.com/tonycpsu/mlbstreamer
Author: Tony Cebzanov
Author-email: tonycpsu@gmail.com
License: GPLv2
Platform: UNKNOWN
Classifier: Environment :: Console
Classifier: License :: OSI Approved :: GNU General Public License v2 (GPLv2)
Classifier: Intended Audience :: End Users/Desktop
